[
    {
        "username": "TheGamer2024",
        "nombre_real": "Alex Mart\u00ednez",
        "followers": 95534,
        "avatar": "1.png",
        "juego_favorito": "Fortnite"
    },
    {
        "username": "ProPlayer99",
        "nombre_real": "Sara Garc\u00eda",
        "followers": 60361,
        "avatar": "10.png",
        "juego_favorito": "LOL"
    },
    {
        "username": "EpicStreamer",
        "nombre_real": "Carlos L\u00f3pez",
        "followers": 86579,
        "avatar": "11.png",
        "juego_favorito": "Fortnite"
    },
    {
        "username": "GameMaster",
        "nombre_real": "Marta Rodr\u00edguez",
        "followers": 8349,
        "avatar": "12.png",
        "juego_favorito": "LOL"
    },
    {
        "username": "EliteWarrior",
        "nombre_real": "David Fern\u00e1ndez",
        "followers": 21800,
        "avatar": "13.png",
        "juego_favorito": "Minecraft"
    },
    {
        "username": "ShadowHunter",
        "nombre_real": "Laura Gonz\u00e1lez",
        "followers": 45204,
        "avatar": "14.png",
        "juego_favorito": "Valorant"
    },
    {
        "username": "NeonBlade",
        "nombre_real": "Javier P\u00e9rez",
        "followers": 75700,
        "avatar": "15.png",
        "juego_favorito": "Minecraft"
    },
    {
        "username": "CyberNinja",
        "nombre_real": "Elena S\u00e1nchez",
        "followers": 86854,
        "avatar": "16.png",
        "juego_favorito": "Rocket League"
    },
    {
        "username": "PixelKing",
        "nombre_real": "Daniel Romero",
        "followers": 58645,
        "avatar": "17.png",
        "juego_favorito": "Fall Guys"
    },
    {
        "username": "StreamQueen",
        "nombre_real": "Ana Torres",
        "followers": 40604,
        "avatar": "18.png",
        "juego_favorito": "Rocket League"
    }
]